twaxs/__init__.py
twaxs/auxiliary.py
twaxs/dataset.py
twaxs/plot.py
twaxs-2.1.0.dist-info/LICENSE
twaxs-2.1.0.dist-info/METADATA
twaxs-2.1.0.dist-info/WHEEL
twaxs-2.1.0.dist-info/top_level.txt
twaxs-2.1.0.dist-info/RECORD
